ever/__init__.py
ever/__main__.py
ever/api/__init__.py
ever/api/infer_tool.py
ever/core/__init__.py
ever/core/builder.py
ever/core/checkpoint.py
ever/core/config.py
ever/core/device.py
ever/core/dist.py
ever/core/iterator.py
ever/core/launcher.py
ever/core/logger.py
ever/core/registry.py
ever/core/to.py
ever/data/__init__.py
ever/data/cross_validation.py
ever/data/distributed.py
ever/interface/__init__.py
ever/interface/callback.py
ever/interface/configurable.py
ever/interface/dataloader.py
ever/interface/learning_rate.py
ever/interface/module.py
ever/interface/transform_base.py
ever/magic/__init__.py
ever/magic/bigimage/__init__.py
ever/magic/bigimage/sliding_window.py
ever/magic/transform/__init__.py
ever/magic/transform/segm.py
ever/magic/transform/tta.py
ever/metric/__init__.py
ever/metric/confusion_matrix.py
ever/metric/evaluate_fn.py
ever/metric/function.py
ever/metric/pixel.py
ever/metric/utils.py
ever/module/__init__.py
ever/module/_densenet.py
ever/module/_hrnet.py
ever/module/_resnets.py
ever/module/aspp.py
ever/module/context_block.py
ever/module/deeplabv3p_head.py
ever/module/densenet.py
ever/module/efficientnet.py
ever/module/fpn.py
ever/module/fs_relation.py
ever/module/hrnet.py
ever/module/hrnet_head.py
ever/module/loss.py
ever/module/misc.py
ever/module/ops.py
ever/module/ppm.py
ever/module/resnest.py
ever/module/resnet.py
ever/module/se_block.py
ever/module/dinov3/__init__.py
ever/module/dinov3/layers/__init__.py
ever/module/dinov3/layers/attention.py
ever/module/dinov3/layers/block.py
ever/module/dinov3/layers/dino_head.py
ever/module/dinov3/layers/ffn_layers.py
ever/module/dinov3/layers/fp8_linear.py
ever/module/dinov3/layers/layer_scale.py
ever/module/dinov3/layers/patch_embed.py
ever/module/dinov3/layers/rms_norm.py
ever/module/dinov3/layers/rope_position_encoding.py
ever/module/dinov3/layers/sparse_linear.py
ever/module/dinov3/models/__init__.py
ever/module/dinov3/models/convnext.py
ever/module/dinov3/models/vision_transformer.py
ever_beta-0.5.3.dist-info/licenses/LICENSE
ever_beta-0.5.3.dist-info/METADATA
ever_beta-0.5.3.dist-info/WHEEL
ever_beta-0.5.3.dist-info/top_level.txt
ever_beta-0.5.3.dist-info/RECORD
