Metadata-Version: 2.4
Name: ever_beta
Version: 0.5.3
Summary: A Library for Earth Vision Researcher
Author-email: Zhuo Zheng <zhuozheng@cs.stanford.edu>
License: Copyright (c) Zhuo Zheng. All rights reserved                                 
Keywords: Remote Sensing,Earth Vision,Deep Learning,Object Detection,Semantic Segmentation,Image Classification,Change Detection
Classifier: Development Status :: 4 - Beta
Classifier: License :: OSI Approved :: Apache Software License
Classifier: Operating System :: OS Independent
Classifier: Programming Language :: Python :: 3.8
Classifier: Programming Language :: Python :: 3.9
Classifier: Programming Language :: Python :: 3.10
Classifier: Programming Language :: Python :: 3.11
Classifier: Topic :: Scientific/Engineering :: Artificial Intelligence
Classifier: Topic :: Scientific/Engineering :: GIS
Requires-Python: >=3.8
License-File: LICENSE
Requires-Dist: numpy
Requires-Dist: prettytable
Requires-Dist: Pillow
Requires-Dist: albumentations
Requires-Dist: tensorboard>=1.14
Requires-Dist: tifffile
Requires-Dist: scikit-image
Requires-Dist: matplotlib
Requires-Dist: tqdm
Requires-Dist: pandas
Requires-Dist: wandb
Requires-Dist: einops
Requires-Dist: huggingface_hub
Dynamic: license-file
